enstadtpfaff_platform_mock_api/__init__.py
enstadtpfaff_platform_mock_api/event.py
enstadtpfaff_platform_mock_api/event_broker.py
enstadtpfaff_platform_mock_api/platform_mock_api.py
enstadtpfaff_platform_mock_api/platform_mock_api_factory.py
enstadtpfaff_platform_mock_api/event_builders/__init__.py
enstadtpfaff_platform_mock_api/event_builders/services/__init__.py
enstadtpfaff_platform_mock_api/event_builders/services/echo_service.py
enstadtpfaff_platform_mock_api/event_builders/shared/__init__.py
enstadtpfaff_platform_mock_api/event_builders/shared/appointments.py
enstadtpfaff_platform_mock_api/event_builders/shared/chat_messages.py
enstadtpfaff_platform_mock_api/event_builders/shared/hints.py
enstadtpfaff_platform_mock_api/event_builders/shared/platform_events.py
enstadtpfaff_platform_mock_api/event_builders/shared/smart_home.py
enstadtpfaff_platform_mock_api/util/__init__.py
enstadtpfaff_platform_mock_api/util/constants.py
enstadtpfaff_platform_mock_api/util/topic_type.py
enstadtpfaff_platform_mock_api/util/topic_util.py
enstadtpfaff_platform_mock_api-0.5.1.dist-info/METADATA
enstadtpfaff_platform_mock_api-0.5.1.dist-info/WHEEL
enstadtpfaff_platform_mock_api-0.5.1.dist-info/top_level.txt
enstadtpfaff_platform_mock_api-0.5.1.dist-info/RECORD
