Metadata-Version: 2.1
Name: enstadtpfaff-platform-mock-api
Version: 0.5.1
Summary: This is the Python API for the EnStadt:Pfaff Platform Mock
Home-page: UNKNOWN
Author: Platform Development Team
Author-email: platform-dev@iese.fraunhofer.de
License: UNKNOWN
Platform: UNKNOWN
Requires-Dist: paho-mqtt
Requires-Dist: PySocks
